{
  "monday": [
    {
      "name": "Quantitative Methods",
      "tutor": "Indira Khadjieva",
      "format": "online lecture",
      "start": 9.0,
      "length": 2.0,
      "location": "IB309"
    },
    {
      "name": "I, Citizen",
      "tutor": "Ijobat Juraeva",
      "format": "seminar",
      "start": 12.0,
      "length": 2.0,
      "location": "SHB207"
    }
  ],
  "tuesday": [
    {
      "name": "Academic English",
      "tutor": "Dildora Tashpulatova",
      "format": "seminar",
      "start": 9.0,
      "length": 2.0,
      "location": "SHB503"
    }
  ],
  "wednesday": [
    {
      "name": "Developing Professional  Identity",
      "tutor": "Jasur Khudoyberdiev",
      "format": "seminar",
      "start": 9.0,
      "length": 2.0,
      "location": "SHB207"
    }
  ],
  "thursday": [
    {
      "name": "Academic English",
      "tutor": "Dildora Tashpulatova",
      "format": "seminar",
      "start": 9.0,
      "length": 2.0,
      "location": "SHB503"
    }
  ],
  "friday": [
    {
      "name": "Quantitative Methods",
      "tutor": "Kamolakhon Alikulova",
      "format": "seminar",
      "start": 11.0,
      "length": 2.0,
      "location": "IB216"
    }
  ],
  "saturday": []
}